{"name":"大模型","slug":"大模型","count":1,"postlist":[{"title":"大模型学习","uid":"790f0da8c2ac27cfc9217b88b39debdd","slug":"大模型学习","date":"2025-07-01T22:01:02.000Z","updated":"2025-07-03T02:17:06.206Z","comments":true,"path":"api/articles/大模型学习.json","keywords":null,"cover":null,"text":"知识点： RNN：用于处理序列数据的神经网络，比FNN多“记忆”能力 https://www.runoob.com/nlp/recurrent-neural-n...","permalink":"/post/大模型学习","photos":[],"count_time":{"symbolsCount":185,"symbolsTime":"1 mins."},"categories":[],"tags":[{"name":"大模型","slug":"大模型","count":1,"path":"api/tags/大模型.json"}],"author":{"name":"蜗角虚名羊","slug":"blog-author","avatar":"/pictures/logo.jpg","link":"/","description":"<p>暂时还没想到要说什么<br>但又不想留白</p>","socials":{"github":"https://github.com/xmy1107","twitter":"","stackoverflow":"","wechat":"","qq":"","weibo":"","zhihu":"","csdn":"https://blog.csdn.net/xumingyang0","juejin":"","customs":{}}}}]}